pysleuth-0.1.3.dist-info/METADATA
pysleuth-0.1.3.dist-info/WHEEL
pysleuth-0.1.3.dist-info/entry_points.txt
pysleuth-0.1.3.dist-info/licenses/LICENSE
pysleuth/__init__.py
pysleuth/__main__.py
pysleuth/pysleuth.cpython-310-darwin.so
pysleuth-0.1.3.dist-info/RECORD
