Metadata-Version: 2.4
Name: pysleuth
Version: 0.1.3
License-File: LICENSE
Summary: A tool to analyze Python code for potential error.
Author: Shuduo Sang <sangshuduo@gmail.com>
Author-email: Shudou Sang <sangshuduo@gmail.com>
License: MIT
Requires-Python: >=3.6
Project-URL: Repository, https://github.com/sangshuduo/pysleuth
